feast_azure_provider_temp/__init__.py
feast_azure_provider_temp/azure_provider.py
feast_azure_provider_temp/mssqlserver.py
feast_azure_provider_temp/mssqlserver_source.py
feast_azure_provider_temp/registry_store.py
feast_azure_provider_temp-0.2.0.dist-info/METADATA
feast_azure_provider_temp-0.2.0.dist-info/WHEEL
feast_azure_provider_temp-0.2.0.dist-info/top_level.txt
feast_azure_provider_temp-0.2.0.dist-info/RECORD
