Metadata-Version: 2.1
Name: feast-azure-provider-temp
Version: 0.2.0
Summary: A Feast Azure Provider
Author: Microsoft
License: MIT
Classifier: License :: OSI Approved :: MIT License
Classifier: Programming Language :: Python
Classifier: Programming Language :: Python :: 3
Classifier: Programming Language :: Python :: 3.8
Requires-Python: >=3.8.1, <=3.8.12
Requires-Dist: feast[redis] (==0.19.4)
Requires-Dist: databricks-connect (==9.1.*)
Requires-Dist: azure-storage-blob (>=0.37.0)
Requires-Dist: azure-identity (>=1.6.1)
Provides-Extra: dev
Requires-Dist: pytest ; extra == 'dev'
Requires-Dist: mypy ; extra == 'dev'
Requires-Dist: assertpy ; extra == 'dev'
Provides-Extra: snowflake
Requires-Dist: snowflake-connector-python[pandas] (>=2.7.3) ; extra == 'snowflake'
